tomo_twin/__init__.py
tomo_twin/gt_generators.py
tomo_twin/pg_filter.py
tomo_twin/ray.py
tomo_twin/recon.py
tomo_twin-1.10.dist-info/LICENSE.md
tomo_twin-1.10.dist-info/METADATA
tomo_twin-1.10.dist-info/WHEEL
tomo_twin-1.10.dist-info/top_level.txt
tomo_twin-1.10.dist-info/RECORD
