Metadata-Version: 2.1
Name: tomo-twin
Version: 1.10
Summary: A simple digital twin for synchrotron tomography
Home-page: https://github.com/aniketkt/TomoTwin
Author: Aniket Tekawade
Author-email: atekawade@anl.gov
License: BSD
Platform: UNKNOWN
Requires-Dist: numpy
Requires-Dist: pandas
Requires-Dist: scipy
Requires-Dist: h5py
Requires-Dist: matplotlib
Requires-Dist: opencv-python
Requires-Dist: porespy
Requires-Dist: ConfigArgParse
Requires-Dist: tqdm
Requires-Dist: ipython
Requires-Dist: ct-segnet
